{
    "play": "play",
    "joue": "play",
    "joues": "play",
    "jouer": "play",
    "lance": "play",
    "lances": "play",
    "lancer": "play",
    "écouter": "play",
    "arrête": "stop",
    "arrêtes": "stop",
    "arrêter": "stop",
    "stop": "stop",
    "stoppe": "stop",
    "stoppes": "stop",
    "pause": "pause",
    "pose": "pause",
    "resume": "resume",
    "reprend": "resume",
    "reprends": "resume",
    "reprendre": "resume",
    "monte": "up",
    "montes": "up",
    "monter": "up",
    "augmente": "up",
    "augmentes": "up",
    "augmenter": "up",
    "baisse": "down",
    "baisses": "down",
    "baisser": "down",
    "diminue": "down",
    "diminues": "down",
    "diminuer": "down"
}